MANIFEST.in
README.md
setup.cfg
setup.py
errant/__init__.py
errant/checker.py
errant/compare_m2.py
errant/m2_to_m2.py
errant/parallel_to_m2.py
errant/resources/en-ptb_map
errant/resources/en_GB-large.txt
errant/scripts/__init__.py
errant/scripts/align_text.py
errant/scripts/cat_rules.py
errant/scripts/rdlextra.py
errant/scripts/toolbox.py
errant_qordoba.egg-info/PKG-INFO
errant_qordoba.egg-info/SOURCES.txt
errant_qordoba.egg-info/dependency_links.txt
errant_qordoba.egg-info/requires.txt
errant_qordoba.egg-info/top_level.txt