Metadata-Version: 1.2
Name: errant-qordoba
Version: 1.1.6
Summary: ERRor ANnotation Toolkit: Automatically extract and classify grammatical errors in parallel original and corrected sentences.
Home-page: https://github.com/Qordobacode/errant
Author: Christopher Bryant, Mariano Felice
License: MIT
Keywords: error annotation toolkit,grammatical correction errors,,grammatical errors,,grammatical correction,GEC
Platform: UNKNOWN
Classifier: Development Status :: 5 - Production/Stable
Classifier: Intended Audience :: Developers
Classifier: Intended Audience :: Science/Research
Classifier: Topic :: Scientific/Engineering :: Artificial Intelligence
Classifier: Topic :: Text Processing :: Linguistic
Classifier: License :: OSI Approved :: MIT License
Classifier: Programming Language :: Python :: 3.4
Classifier: Programming Language :: Python :: 3.5
Classifier: Programming Language :: Python :: 3.6
Classifier: Programming Language :: Python :: 3.7
Requires-Python: >=3.4.0
